easy_example_pkg/__init__.py
easy_example_pkg/example.py
easy_example_pkg-0.0.1.dist-info/LICENSE
easy_example_pkg-0.0.1.dist-info/METADATA
easy_example_pkg-0.0.1.dist-info/WHEEL
easy_example_pkg-0.0.1.dist-info/top_level.txt
easy_example_pkg-0.0.1.dist-info/RECORD
