Metadata-Version: 2.1
Name: easy-example-pkg
Version: 0.0.1
Summary: A A small example package
Home-page: https://github.com/chen955/AI
Author: chen955
Author-email: zk__Chen@163.com
License: UNKNOWN
Platform: UNKNOWN
Classifier: Programming Language :: Python :: 3
Classifier: License :: OSI Approved :: MIT License
Classifier: Operating System :: OS Independent
